fourch/__init__.py
fourch/api.py
fourch/const.py
fourch/exceptions.py
fourch/models.py
fourch/session.py
fourch-0.1.1.dist-info/METADATA
fourch-0.1.1.dist-info/WHEEL
fourch-0.1.1.dist-info/RECORD
