Metadata-Version: 2.1
Name: fourch
Version: 0.1.1
Summary: 
Author: BazZziliuS
Requires-Python: >=3.12
Classifier: Programming Language :: Python :: 3
Classifier: Programming Language :: Python :: 3.12
Requires-Dist: aiohttp (>=3.9.3)
Requires-Dist: pydantic (>=2.5.2)
